app/__init__.py
app/c_pipeline_xml_to_csv.py
app/c_single_test_csv.py
app/c_xml_display_elements.py
app/c_xml_manager.py
app/c_xml_structure.py
app/c_xml_xslt_logic.py
app/cli.py
app/pipeline_test_csv.py
app/pipeline_xml_connect.py
app/pipeline_xml_to_csv.py
app/prod_xml_to_csv.py
app/single_test_csv.py
app/xml_connect.py
app/xml_manager.py
app/xml_structure.py
app/xml_to_csv
xmlvault-0.0.33.dist-info/LICENSE
xmlvault-0.0.33.dist-info/METADATA
xmlvault-0.0.33.dist-info/WHEEL
xmlvault-0.0.33.dist-info/entry_points.txt
xmlvault-0.0.33.dist-info/RECORD
